[
  {
    "id": 1,
    "examen": "nombre_del_pdf",
    "id_pregunta": "ejemplo_01",
    "pregunta": "pregunta 1",
    "opciones": {
      "a": "sistema1",
      "b": "sistema2",
      "c": "sistema3",
      "d": "sistema4"
    },
    "respuesta_correcta": "null",
    "tema": "null"
  },
  {
    "id": 2,
    "examen": "nombre_del_pdf",
    "id_pregunta": "ejemplo_02",
    "pregunta": "pregunta 2",
    "opciones": {
      "a": "op1",
      "b": "op2",
      "c": "op3",
      "d": "op4"
    },
    "respuesta_correcta": "null",
    "tema": "null"
  },
  {
    "id": 3,
    "examen": "nombre_del_pdf",
    "id_pregunta": "ejemplo_03",
    "pregunta": "preguntita3",
    "opciones": {
      "a": "preguntita2",
      "b": "pregunttitai2",
      "c": "asdfas",
      "d": "asdfsdf"
    },
    "respuesta_correcta": "null",
    "tema": "null"
  }
]